egret/EgretCleanBigWideFormatTransformer.py
egret/EgretCleanCategoricalMasker.py
egret/EgretCleanDropColTransformer.py
egret/EgretCleanDropContinuousValuesTransformer.py
egret/EgretCleanDummyTransformer.py
egret/EgretCleanPDCNullFillerTransformer.py
egret/EgretCleanPassthroughTransformer.py
egret/__init__.py
egret/egret.py
hippo/HippoOutcomePredictionTranche.py
hippo/HippoRowRandomizerMasker.py
hippo/HippoShapTransformer.py
hippo/HippoXgboostModel.py
hippo/__init__.py
hippo/hippo.py
moose/MooseColumnCareGapOpenCountTransformer.py
moose/MooseColumnFillerTransformer.py
moose/MooseColumnMoldMarginalTransformer.py
moose/MooseColumnMultiplicationTransformer.py
moose/MooseColumnTypeSetTransformer.py
moose/MooseGapOAReportOutput.py
moose/MooseKeepNamedColumnsTransformer.py
moose/MooseKeeperOffenderDrugCountTransformer.py
moose/MooseKeeperOffenderDrugTypeTransformer.py
moose/MooseKeeperOffenderDuplicateTransformer.py
moose/MooseKeeperOffenderMutuallyExclusiveTransformer.py
moose/MooseKeeperOffenderPipeline.py
moose/MooseKeeperOffenderTranche.py
moose/MooseLineOfBusinessOneColumnTransformer.py
moose/MooseListOfTupleLengthTransformer.py
moose/MooseMemberGapLevelPipeline.py
moose/MooseMemberGapTallChannelTransformer.py
moose/MooseMemberGapTallProbabilityTransformer.py
moose/MooseMemberGapTallTransformer.py
moose/MooseMemberLevelPipeline.py
moose/MooseOpenCareGapImpactListFastTransformer.py
moose/MooseOpenCareGapImpactListTransformer.py
moose/MooseROIReportOutput.py
moose/MooseShapCostColumnTransformer.py
moose/MooseShapImpactOutput.py
moose/__init__.py
moose/moose.py
otter/OtterA1cImputation.py
otter/OtterCareConsiderationComAggregatePipeline.py
otter/OtterCareConsiderationMedAggregatePipeline.py
otter/OtterCareConsiderationPipeline.py
otter/OtterCareConsiderationTransformer.py
otter/OtterCareGapAllOptionColTransformer.py
otter/OtterCareGapColumnConsolidater.py
otter/OtterCareGapComComorbidityAggregatePipeline.py
otter/OtterCareGapComComorbidityPipeline.py
hippo_diabetes-1.0.0.dist-info/METADATA
hippo_diabetes-1.0.0.dist-info/WHEEL
hippo_diabetes-1.0.0.dist-info/top_level.txt
hippo_diabetes-1.0.0.dist-info/RECORD
