Metadata-Version: 2.1
Name: hippo-diabetes
Version: 1.0.0
Summary: Hippo package
Home-page: https://github.aetna.com/clinical-product-analytics/hippo/tree/master/src2
Author: author
Author-email: author@gmail.com
License: UNKNOWN
Platform: UNKNOWN
Classifier: Programming Language :: Python :: 3
Classifier: License :: OSI Approved :: MIT License
Classifier: Operating System :: OS Independent
Requires-Python: >=3.6
